spotifyfizyfit/__init__.py
spotifyfizyfit/runner.py
spotifyfizyfit-1.0.8.dist-info/LICENSE
spotifyfizyfit-1.0.8.dist-info/METADATA
spotifyfizyfit-1.0.8.dist-info/WHEEL
spotifyfizyfit-1.0.8.dist-info/entry_points.txt
spotifyfizyfit-1.0.8.dist-info/top_level.txt
spotifyfizyfit-1.0.8.dist-info/RECORD
