Metadata-Version: 2.1
Name: spotifyfizyfit
Version: 1.0.8
Summary: spotifyfizyfit, a tool to migrate your Spotify playlists
Home-page: https://github.com/fleizean/spotifyfizyfit
Author: fleizean (Enes Yagiz)
Author-email: nsyagz@gmail.com
License: MIT
Keywords: spotify fizy playlist migration
Classifier: Programming Language :: Python :: 3
Classifier: License :: OSI Approved :: MIT License
Classifier: Operating System :: POSIX :: Linux
Classifier: Operating System :: MacOS
Classifier: Operating System :: Microsoft :: Windows
License-File: LICENSE
Requires-Dist: selenium
Requires-Dist: colorama
